faster_async_lru.cp314-win_amd64.pyd
faster_async_lru/__init__.py
faster_async_lru/py.typed
faster_async_lru-2.0.5.3.dist-info/licenses/LICENSE
faster_async_lru-2.0.5.3.dist-info/METADATA
faster_async_lru-2.0.5.3.dist-info/WHEEL
faster_async_lru-2.0.5.3.dist-info/top_level.txt
faster_async_lru-2.0.5.3.dist-info/RECORD
